ws_data_extractor/__init__.py
ws_data_extractor/client.py
ws_data_extractor/errors.py
ws_data_extractor/models.py
ws_data_extractor/py.typed
ws_data_extractor/utils.py
ws_data_extractor-0.1.0.dist-info/licenses/LICENSE
ws_data_extractor-0.1.0.dist-info/METADATA
ws_data_extractor-0.1.0.dist-info/WHEEL
ws_data_extractor-0.1.0.dist-info/top_level.txt
ws_data_extractor-0.1.0.dist-info/RECORD
