Metadata-Version: 2.4
Name: ws-data-extractor
Version: 0.1.0
Summary: Python client for the Web Scraper Data Extractor API
License-Expression: MIT
Classifier: Programming Language :: Python :: 3
Classifier: Programming Language :: Python :: 3 :: Only
Classifier: Programming Language :: Python :: 3.9
Classifier: Programming Language :: Python :: 3.10
Classifier: Programming Language :: Python :: 3.11
Classifier: Programming Language :: Python :: 3.12
Classifier: Programming Language :: Python :: 3.13
Requires-Python: >=3.9
License-File: LICENSE
Requires-Dist: httpx>=0.24
Provides-Extra: release
Requires-Dist: build>=1.2.1; extra == "release"
Requires-Dist: twine>=5.0.0; extra == "release"
Dynamic: license-file
